{
  "@context": "http://id.who.int/icd/contexts/contextForLinearizationEntity.json",
  "@id": "http://id.who.int/icd/release/11/2024-01/mms/1019362950",
  "parent": [
    "http://id.who.int/icd/release/11/2024-01/mms/1375406603"
  ],
  "browserUrl": "https://icd.who.int/browse/2024-01/mms/en#1019362950",
  "code": "XN1V8",
  "source": "http://id.who.int/icd/entity/1019362950",
  "classKind": "category",
  "title": {
    "@language": "en",
    "@value": "Severe Acute Respiratory Syndrome coronavirus"
  },
  "indexTerm": [
    {
      "label": {
        "@language": "en",
        "@value": "Severe Acute Respiratory Syndrome coronavirus"
      }
    },
    {
      "label": {
        "@language": "en",
        "@value": "SARS-CoV"
      }
    }
  ]
}