{
  "@context": "http://id.who.int/icd/contexts/contextForLinearizationEntity.json",
  "@id": "http://id.who.int/icd/release/11/2024-01/mms/1031219789",
  "parent": [
    "http://id.who.int/icd/release/11/2024-01/mms/1917297026"
  ],
  "browserUrl": "https://icd.who.int/browse/2024-01/mms/en#1031219789",
  "code": "1C11.00",
  "source": "http://id.who.int/icd/entity/1031219789",
  "classKind": "category",
  "title": {
    "@language": "en",
    "@value": "Oroya fever"
  },
  "definition": {
    "@language": "en",
    "@value": "A disease commonly caused by an infection with the gram-negative bacteria Bartonella bacilliformis. This disease is characterised by severe haemolytic anaemia and transient immunosuppression. This disease may present with fever, malaise, or jaundice. Transmission is through the bite of infected sandflies from the genus Lutzomyia. Confirmation is by identification of Bartonella bacilliformis in a blood sample."
  },
  "longDefinition": {
    "@language": "en",
    "@value": "Oroya fever is a bacteraemic form of infection with Bartonella bacilliformis. Transmission is by bite from an infected Lutzomyia sand-fly, a type found only in the high Andes (>1000 metres). There is an incubation period of 3-12 weeks. The illness may range from mild to very severe. In severe cases, fever, chills, headache, sweating, aches, dyspnoea, confusion and seizures may occur."
  },
  "relatedEntitiesInPerinatalChapter": [
    "http://id.who.int/icd/entity/1935107489"
  ],
  "indexTerm": [
    {
      "label": {
        "@language": "en",
        "@value": "Oroya fever"
      }
    },
    {
      "label": {
        "@language": "en",
        "@value": "Systemic bartonellosis due to Bartonella bacilliformis"
      }
    },
    {
      "label": {
        "@language": "en",
        "@value": "Systemic Carrión disease"
      }
    },
    {
      "label": {
        "@language": "en",
        "@value": "systemic bartonellosis"
      }
    },
    {
      "label": {
        "@language": "en",
        "@value": "Bartonella fever"
      }
    }
  ]
}