{
  "@context": "http://id.who.int/icd/contexts/contextForLinearizationEntity.json",
  "@id": "http://id.who.int/icd/release/11/2024-01/mms/1042894837",
  "parent": [
    "http://id.who.int/icd/release/11/2024-01/mms/1936976727"
  ],
  "browserUrl": "https://icd.who.int/browse/2024-01/mms/en#1042894837",
  "code": "XH5TR7",
  "source": "http://id.who.int/icd/entity/1042894837",
  "classKind": "category",
  "title": {
    "@language": "en",
    "@value": "Adenocarcinoma of lung, mixed mucinous and non-mucinous"
  },
  "indexTerm": [
    {
      "label": {
        "@language": "en",
        "@value": "Adenocarcinoma of lung, mixed mucinous and non-mucinous"
      }
    },
    {
      "label": {
        "@language": "en",
        "@value": "Bronchiolo-alveolar carcinoma, Clara cell and goblet cell type"
      }
    },
    {
      "label": {
        "@language": "en",
        "@value": "Bronchiolo-alveolar carcinoma, type II pneumocyte and goblet cell type"
      }
    },
    {
      "label": {
        "@language": "en",
        "@value": "Bronchiolo-alveolar carcinoma, indeterminate type"
      }
    },
    {
      "label": {
        "@language": "en",
        "@value": "Bronchiolo-alveolar carcinoma, mixed mucinous and non-mucinous"
      }
    }
  ]
}