{
  "@context": "http://id.who.int/icd/contexts/contextForLinearizationEntity.json",
  "@id": "http://id.who.int/icd/release/11/2024-01/mms/1258542550",
  "parent": [
    "http://id.who.int/icd/release/11/2024-01/mms/1133981605"
  ],
  "browserUrl": "https://icd.who.int/browse/2024-01/mms/en#1258542550",
  "code": "XA0FR0",
  "source": "http://id.who.int/icd/entity/1258542550",
  "classKind": "category",
  "title": {
    "@language": "en",
    "@value": "Fascia"
  },
  "indexTerm": [
    {
      "label": {
        "@language": "en",
        "@value": "Fascia"
      }
    }
  ]
}