{
  "@context": "http://id.who.int/icd/contexts/contextForLinearizationEntity.json",
  "@id": "http://id.who.int/icd/release/11/2024-01/mms/1342340145",
  "parent": [
    "http://id.who.int/icd/release/11/2024-01/mms/1594880101"
  ],
  "browserUrl": "https://icd.who.int/browse/2024-01/mms/en#1342340145",
  "code": "XE3WH",
  "source": "http://id.who.int/icd/entity/1342340145",
  "classKind": "category",
  "title": {
    "@language": "en",
    "@value": "Person responsible to resume manual control of a vehicle under autonomous or partly autonomous control injured in transport related event"
  },
  "indexTerm": [
    {
      "label": {
        "@language": "en",
        "@value": "Person responsible to resume manual control of a vehicle under autonomous or partly autonomous control injured in transport related event"
      }
    }
  ]
}