{
  "@context": "http://id.who.int/icd/contexts/contextForLinearizationEntity.json",
  "@id": "http://id.who.int/icd/release/11/2024-01/mms/1367598280",
  "parent": [
    "http://id.who.int/icd/release/11/2024-01/mms/1080392099"
  ],
  "browserUrl": "https://icd.who.int/browse/2024-01/mms/en#1367598280",
  "code": "1F25.00",
  "source": "http://id.who.int/icd/entity/1367598280",
  "classKind": "category",
  "postcoordinationScale": [
    {
      "@id": "http://id.who.int/icd/release/11/2024-01/mms/1367598280/postcoordinationScale/specificAnatomy",
      "axisName": "http://id.who.int/icd/schema/specificAnatomy",
      "requiredPostcoordination": "false",
      "allowMultipleValues": "AllowAlways",
      "scaleEntity": [
        "http://id.who.int/icd/release/11/2024-01/mms/1983574845",
        "http://id.who.int/icd/release/11/2024-01/mms/922044675",
        "http://id.who.int/icd/release/11/2024-01/mms/1013784154"
      ]
    },
    {
      "@id": "http://id.who.int/icd/release/11/2024-01/mms/1367598280/postcoordinationScale/hasManifestation",
      "axisName": "http://id.who.int/icd/schema/hasManifestation",
      "requiredPostcoordination": "false",
      "allowMultipleValues": "AllowAlways",
      "scaleEntity": [
        "http://id.who.int/icd/release/11/2024-01/mms/2024199586",
        "http://id.who.int/icd/release/11/2024-01/mms/1765820617",
        "http://id.who.int/icd/release/11/2024-01/mms/189285942",
        "http://id.who.int/icd/release/11/2024-01/mms/795057595",
        "http://id.who.int/icd/release/11/2024-01/mms/1298895686",
        "http://id.who.int/icd/release/11/2024-01/mms/1552748079"
      ]
    }
  ],
  "title": {
    "@language": "en",
    "@value": "Acute pulmonary coccidioidomycosis"
  },
  "definition": {
    "@language": "en",
    "@value": "Forty per cent of coccidioidal infections result in symptomatic pulmonary disease that may be indistinguishable from a bacterial community-acquired pneumonia. Radiographically these are usually focal alveolar infiltrates. Infection may be associated with the development of a rash, particularly erythema nodosum and erythema multiforme. Occasionally, there may be symmetric arthralgias or arthritis. Peripheral blood eosinophilia is not uncommon. Acute primary pulmonary coccidioidomycosis, particularly when associated with erythema nodosum and/or erythema multiforme, is frequently called \"Valley fever.\" When associated with arthralgias or arthritis, it has been termed \"desert rheumatism.\""
  },
  "relatedEntitiesInPerinatalChapter": [
    "http://id.who.int/icd/entity/528118622"
  ],
  "indexTerm": [
    {
      "label": {
        "@language": "en",
        "@value": "Acute pulmonary coccidioidomycosis"
      }
    },
    {
      "label": {
        "@language": "en",
        "@value": "desert fever"
      }
    },
    {
      "label": {
        "@language": "en",
        "@value": "desert rheumatism"
      }
    },
    {
      "label": {
        "@language": "en",
        "@value": "San Joaquin fever"
      }
    },
    {
      "label": {
        "@language": "en",
        "@value": "San Joaquin valley fever"
      }
    },
    {
      "label": {
        "@language": "en",
        "@value": "valley fever"
      }
    },
    {
      "label": {
        "@language": "en",
        "@value": "primary pulmonary coccidioidomycosis"
      }
    },
    {
      "label": {
        "@language": "en",
        "@value": "pulmonary coccidioidomycosis NOS"
      }
    }
  ]
}