{
  "@context": "http://id.who.int/icd/contexts/contextForLinearizationEntity.json",
  "@id": "http://id.who.int/icd/release/11/2024-01/mms/1697216126",
  "parent": [
    "http://id.who.int/icd/release/11/2024-01/mms/1958761246"
  ],
  "browserUrl": "https://icd.who.int/browse/2024-01/mms/en#1697216126",
  "code": "MF54.1",
  "source": "http://id.who.int/icd/entity/1697216126",
  "classKind": "category",
  "title": {
    "@language": "en",
    "@value": "Irregularly contracted kidney"
  },
  "definition": {
    "@language": "en",
    "@value": "A kidney with deep cortical indentations or scars large enough to be perceived or examined by the naked eye"
  },
  "indexTerm": [
    {
      "label": {
        "@language": "en",
        "@value": "Irregularly contracted kidney"
      }
    },
    {
      "label": {
        "@language": "en",
        "@value": "Irregularly contracted kidney associated with a cause classified elsewhere"
      },
      "foundationReference": "http://id.who.int/icd/entity/496048752"
    }
  ]
}