{
  "@context": "http://id.who.int/icd/contexts/contextForLinearizationEntity.json",
  "@id": "http://id.who.int/icd/release/11/2024-01/mms/1817060832",
  "parent": [
    "http://id.who.int/icd/release/11/2024-01/mms/35921102"
  ],
  "browserUrl": "https://icd.who.int/browse/2024-01/mms/en#1817060832",
  "code": "XN1XN",
  "source": "http://id.who.int/icd/entity/1817060832",
  "classKind": "category",
  "title": {
    "@language": "en",
    "@value": "Circulating vaccine-derived poliovirus type 2"
  },
  "indexTerm": [
    {
      "label": {
        "@language": "en",
        "@value": "Circulating vaccine-derived poliovirus type 2"
      }
    },
    {
      "label": {
        "@language": "en",
        "@value": "cVDPV2"
      }
    }
  ]
}