{
  "@context": "http://id.who.int/icd/contexts/contextForLinearizationEntity.json",
  "@id": "http://id.who.int/icd/release/11/2024-01/mms/2013768320",
  "parent": [
    "http://id.who.int/icd/release/11/2024-01/mms/2108063439"
  ],
  "browserUrl": "https://icd.who.int/browse/2024-01/mms/en#2013768320",
  "code": "XA1E00",
  "source": "http://id.who.int/icd/entity/2013768320",
  "classKind": "category",
  "foundationChildElsewhere": [
    {
      "label": {
        "@language": "en",
        "@value": "Optic chiasm"
      },
      "foundationReference": "http://id.who.int/icd/entity/1790942493",
      "linearizationReference": "http://id.who.int/icd/release/11/2024-01/mms/1790942493"
    },
    {
      "label": {
        "@language": "en",
        "@value": "Optic tract"
      },
      "foundationReference": "http://id.who.int/icd/entity/2107111901",
      "linearizationReference": "http://id.who.int/icd/release/11/2024-01/mms/2107111901"
    }
  ],
  "title": {
    "@language": "en",
    "@value": "Optic nerve"
  },
  "indexTerm": [
    {
      "label": {
        "@language": "en",
        "@value": "Optic nerve"
      }
    },
    {
      "label": {
        "@language": "en",
        "@value": "Second Cranial Nerve"
      }
    }
  ]
}