{
  "@context": "http://id.who.int/icd/contexts/contextForLinearizationEntity.json",
  "@id": "http://id.who.int/icd/release/11/2024-01/mms/2074261372",
  "parent": [
    "http://id.who.int/icd/release/11/2024-01/mms/845687188"
  ],
  "browserUrl": "https://icd.who.int/browse/2024-01/mms/en#2074261372",
  "code": "DA50.2",
  "source": "http://id.who.int/icd/entity/2074261372",
  "classKind": "category",
  "postcoordinationScale": [
    {
      "@id": "http://id.who.int/icd/release/11/2024-01/mms/2074261372/postcoordinationScale/hasManifestation",
      "axisName": "http://id.who.int/icd/schema/hasManifestation",
      "requiredPostcoordination": "false",
      "allowMultipleValues": "AllowAlways",
      "scaleEntity": [
        "http://id.who.int/icd/release/11/2024-01/mms/1020615731"
      ]
    }
  ],
  "title": {
    "@language": "en",
    "@value": "Fistula of duodenum"
  },
  "definition": {
    "@language": "en",
    "@value": "Fistula of duodenum is an opening through the duodenal wall and into the peritoneal cavity, into another organ and vessels that normally do not connect, or through the abdominal wall."
  },
  "relatedEntitiesInMaternalChapter": [
    "http://id.who.int/icd/entity/1135143938"
  ],
  "relatedEntitiesInPerinatalChapter": [
    "http://id.who.int/icd/entity/494951911"
  ],
  "indexTerm": [
    {
      "label": {
        "@language": "en",
        "@value": "Fistula of duodenum"
      }
    }
  ]
}