{
  "@context": "http://id.who.int/icd/contexts/contextForLinearizationEntity.json",
  "@id": "http://id.who.int/icd/release/11/2024-01/mms/2077117325",
  "parent": [
    "http://id.who.int/icd/release/11/2024-01/mms/252518591"
  ],
  "browserUrl": "https://icd.who.int/browse/2024-01/mms/en#2077117325",
  "code": "ND10",
  "source": "http://id.who.int/icd/entity/2077117325",
  "classKind": "category",
  "postcoordinationScale": [
    {
      "@id": "http://id.who.int/icd/release/11/2024-01/mms/2077117325/postcoordinationScale/laterality",
      "axisName": "http://id.who.int/icd/schema/laterality",
      "requiredPostcoordination": "false",
      "allowMultipleValues": "NotAllowed",
      "scaleEntity": [
        "http://id.who.int/icd/release/11/2024-01/mms/627678743",
        "http://id.who.int/icd/release/11/2024-01/mms/271422288",
        "http://id.who.int/icd/release/11/2024-01/mms/876572005",
        "http://id.who.int/icd/release/11/2024-01/mms/1038788978"
      ]
    },
    {
      "@id": "http://id.who.int/icd/release/11/2024-01/mms/2077117325/postcoordinationScale/associatedWith",
      "axisName": "http://id.who.int/icd/schema/associatedWith",
      "requiredPostcoordination": "false",
      "allowMultipleValues": "AllowAlways",
      "scaleEntity": [
        "http://id.who.int/icd/release/11/2024-01/mms/980862652",
        "http://id.who.int/icd/release/11/2024-01/mms/851395624",
        "http://id.who.int/icd/release/11/2024-01/mms/73322695",
        "http://id.who.int/icd/release/11/2024-01/mms/128104623",
        "http://id.who.int/icd/release/11/2024-01/mms/1491356379",
        "http://id.who.int/icd/release/11/2024-01/mms/491063206",
        "http://id.who.int/icd/release/11/2024-01/mms/185842968",
        "http://id.who.int/icd/release/11/2024-01/mms/2143219175",
        "http://id.who.int/icd/release/11/2024-01/mms/558785723",
        "http://id.who.int/icd/release/11/2024-01/mms/850137482/other",
        "http://id.who.int/icd/release/11/2024-01/mms/850137482/unspecified"
      ]
    }
  ],
  "title": {
    "@language": "en",
    "@value": "Injury to toenail"
  },
  "indexTerm": [
    {
      "label": {
        "@language": "en",
        "@value": "Injury to toenail"
      }
    },
    {
      "label": {
        "@language": "en",
        "@value": "damage to toenail NOS"
      }
    },
    {
      "label": {
        "@language": "en",
        "@value": "subungual injury of toes"
      }
    },
    {
      "label": {
        "@language": "en",
        "@value": "Traumatic injury to nail bed or matrix of nail of foot"
      },
      "foundationReference": "http://id.who.int/icd/entity/2001544586"
    },
    {
      "label": {
        "@language": "en",
        "@value": "Avulsion of toenail"
      },
      "foundationReference": "http://id.who.int/icd/entity/792905058"
    },
    {
      "label": {
        "@language": "en",
        "@value": "Contusion of toenail"
      },
      "foundationReference": "http://id.who.int/icd/entity/1341067209"
    },
    {
      "label": {
        "@language": "en",
        "@value": "Open wound of toenail"
      },
      "foundationReference": "http://id.who.int/icd/entity/788565380"
    },
    {
      "label": {
        "@language": "en",
        "@value": "Superficial injury to toenail"
      },
      "foundationReference": "http://id.who.int/icd/entity/831598442"
    },
    {
      "label": {
        "@language": "en",
        "@value": "superficial subungual injury of toe(s)"
      },
      "foundationReference": "http://id.who.int/icd/entity/831598442"
    }
  ]
}