{
  "@context": "http://id.who.int/icd/contexts/contextForLinearizationEntity.json",
  "@id": "http://id.who.int/icd/release/11/2024-01/mms/289916430",
  "parent": [
    "http://id.who.int/icd/release/11/2024-01/mms/628961459"
  ],
  "browserUrl": "https://icd.who.int/browse/2024-01/mms/en#289916430",
  "code": "XA99D0",
  "source": "http://id.who.int/icd/entity/289916430",
  "classKind": "category",
  "title": {
    "@language": "en",
    "@value": "Inferior lacrimal punctum"
  },
  "indexTerm": [
    {
      "label": {
        "@language": "en",
        "@value": "Inferior lacrimal punctum"
      }
    }
  ]
}