{
  "@context": "http://id.who.int/icd/contexts/contextForLinearizationEntity.json",
  "@id": "http://id.who.int/icd/release/11/2024-01/mms/360738219",
  "parent": [
    "http://id.who.int/icd/release/11/2024-01/mms/1434060790"
  ],
  "browserUrl": "https://icd.who.int/browse/2024-01/mms/en#360738219",
  "code": "ED80.41",
  "source": "http://id.who.int/icd/entity/360738219",
  "classKind": "category",
  "title": {
    "@language": "en",
    "@value": "Acne conglobata"
  },
  "definition": {
    "@language": "en",
    "@value": "An uncommon chronic severe inflammatory form of acne characterised by the development of multiple abscesses and sinuses followed by extensive hypertrophic and atrophic scarring. It may be associated with spondyloarthropathy or with other follicular occlusive diseases including dissecting cellulitis of the scalp and hidradenitis suppurativa."
  },
  "indexTerm": [
    {
      "label": {
        "@language": "en",
        "@value": "Acne conglobata"
      }
    },
    {
      "label": {
        "@language": "en",
        "@value": "Conglobate acne"
      }
    },
    {
      "label": {
        "@language": "en",
        "@value": "Follicular occlusion syndrome"
      },
      "foundationReference": "http://id.who.int/icd/entity/1428905921"
    },
    {
      "label": {
        "@language": "en",
        "@value": "Follicular occlusion tetrad"
      },
      "foundationReference": "http://id.who.int/icd/entity/265635449"
    },
    {
      "label": {
        "@language": "en",
        "@value": "Follicular occlusion triad"
      },
      "foundationReference": "http://id.who.int/icd/entity/1710566334"
    }
  ]
}