{
  "@context": "http://id.who.int/icd/contexts/contextForLinearizationEntity.json",
  "@id": "http://id.who.int/icd/release/11/2024-01/mms/452386362",
  "parent": [
    "http://id.who.int/icd/release/11/2024-01/mms/435227771"
  ],
  "child": [
    "http://id.who.int/icd/release/11/2024-01/mms/103374449",
    "http://id.who.int/icd/release/11/2024-01/mms/1667404773",
    "http://id.who.int/icd/release/11/2024-01/mms/399491868",
    "http://id.who.int/icd/release/11/2024-01/mms/1921257102",
    "http://id.who.int/icd/release/11/2024-01/mms/23764250",
    "http://id.who.int/icd/release/11/2024-01/mms/237828591",
    "http://id.who.int/icd/release/11/2024-01/mms/1679904912",
    "http://id.who.int/icd/release/11/2024-01/mms/277610609",
    "http://id.who.int/icd/release/11/2024-01/mms/1976028645",
    "http://id.who.int/icd/release/11/2024-01/mms/145676455",
    "http://id.who.int/icd/release/11/2024-01/mms/1843729715",
    "http://id.who.int/icd/release/11/2024-01/mms/1025913253",
    "http://id.who.int/icd/release/11/2024-01/mms/1802560377",
    "http://id.who.int/icd/release/11/2024-01/mms/1413338122",
    "http://id.who.int/icd/release/11/2024-01/mms/452386362/unspecified"
  ],
  "browserUrl": "https://icd.who.int/browse/2024-01/mms/en#452386362",
  "code": "",
  "source": "http://id.who.int/icd/entity/452386362",
  "classKind": "block",
  "blockId": "BlockL1-NA0",
  "codeRange": "NA00-NA0Z",
  "foundationChildElsewhere": [
    {
      "label": {
        "@language": "en",
        "@value": "Epilepsy due to injuries to the head"
      },
      "foundationReference": "http://id.who.int/icd/entity/1007173668",
      "linearizationReference": "http://id.who.int/icd/release/11/2024-01/mms/1007173668"
    },
    {
      "label": {
        "@language": "en",
        "@value": "Birth injury to face"
      },
      "foundationReference": "http://id.who.int/icd/entity/409494931",
      "linearizationReference": "http://id.who.int/icd/release/11/2024-01/mms/409494931"
    }
  ],
  "title": {
    "@language": "en",
    "@value": "Injuries to the head"
  },
  "exclusion": [
    {
      "label": {
        "@language": "en",
        "@value": "Foreign body in ear"
      },
      "foundationReference": "http://id.who.int/icd/entity/2083535144",
      "linearizationReference": "http://id.who.int/icd/release/11/2024-01/mms/2083535144"
    },
    {
      "label": {
        "@language": "en",
        "@value": "Foreign body in mouth"
      },
      "foundationReference": "http://id.who.int/icd/entity/122192082",
      "linearizationReference": "http://id.who.int/icd/release/11/2024-01/mms/122192082"
    },
    {
      "label": {
        "@language": "en",
        "@value": "Foreign body in larynx"
      },
      "foundationReference": "http://id.who.int/icd/entity/1029768081",
      "linearizationReference": "http://id.who.int/icd/release/11/2024-01/mms/1029768081"
    },
    {
      "label": {
        "@language": "en",
        "@value": "Foreign body in pharynx"
      },
      "foundationReference": "http://id.who.int/icd/entity/1479200261",
      "linearizationReference": "http://id.who.int/icd/release/11/2024-01/mms/1479200261"
    },
    {
      "label": {
        "@language": "en",
        "@value": "Foreign body in nostril"
      },
      "foundationReference": "http://id.who.int/icd/entity/747085562",
      "linearizationReference": "http://id.who.int/icd/release/11/2024-01/mms/747085562"
    },
    {
      "label": {
        "@language": "en",
        "@value": "Burns"
      },
      "foundationReference": "http://id.who.int/icd/entity/163532889",
      "linearizationReference": "http://id.who.int/icd/release/11/2024-01/mms/163532889"
    },
    {
      "label": {
        "@language": "en",
        "@value": "Frostbite"
      },
      "foundationReference": "http://id.who.int/icd/entity/152692065",
      "linearizationReference": "http://id.who.int/icd/release/11/2024-01/mms/152692065"
    },
    {
      "label": {
        "@language": "en",
        "@value": "Foreign body on external eye"
      },
      "foundationReference": "http://id.who.int/icd/entity/144533975",
      "linearizationReference": "http://id.who.int/icd/release/11/2024-01/mms/144533975"
    }
  ],
  "codingNote": {
    "@language": "en",
    "@value": "This Block includes the following:\n• injuries of face [any part]\n• injuries of gum\n• injuries of jaw\n• injuries of oral cavity\n• injuries of palate\n• injuries of periocular area\n• injuries of scalp\n• injuries of temporomandibular joint area\n• injuries of tongue\n• injuries of tooth"
  }
}