{
  "@context": "http://id.who.int/icd/contexts/contextForLinearizationEntity.json",
  "@id": "http://id.who.int/icd/release/11/2024-01/mms/805284915",
  "parent": [
    "http://id.who.int/icd/release/11/2024-01/mms/435227771"
  ],
  "child": [
    "http://id.who.int/icd/release/11/2024-01/mms/1448882621",
    "http://id.who.int/icd/release/11/2024-01/mms/857209897",
    "http://id.who.int/icd/release/11/2024-01/mms/1203416278",
    "http://id.who.int/icd/release/11/2024-01/mms/586244420",
    "http://id.who.int/icd/release/11/2024-01/mms/1361048280",
    "http://id.who.int/icd/release/11/2024-01/mms/877936450",
    "http://id.who.int/icd/release/11/2024-01/mms/1090088893",
    "http://id.who.int/icd/release/11/2024-01/mms/632463913",
    "http://id.who.int/icd/release/11/2024-01/mms/1490794347",
    "http://id.who.int/icd/release/11/2024-01/mms/867689657",
    "http://id.who.int/icd/release/11/2024-01/mms/1079605037",
    "http://id.who.int/icd/release/11/2024-01/mms/805284915/other",
    "http://id.who.int/icd/release/11/2024-01/mms/805284915/unspecified"
  ],
  "browserUrl": "https://icd.who.int/browse/2024-01/mms/en#805284915",
  "code": "",
  "source": "http://id.who.int/icd/entity/805284915",
  "classKind": "block",
  "blockId": "BlockL1-NA8",
  "codeRange": "NA80-NB3Z",
  "foundationChildElsewhere": [
    {
      "label": {
        "@language": "en",
        "@value": "Birth injury of thorax"
      },
      "foundationReference": "http://id.who.int/icd/entity/1142758480",
      "linearizationReference": "http://id.who.int/icd/release/11/2024-01/mms/1142758480"
    }
  ],
  "title": {
    "@language": "en",
    "@value": "Injuries to the thorax"
  },
  "exclusion": [
    {
      "label": {
        "@language": "en",
        "@value": "injuries of spinal cord NOS"
      },
      "foundationReference": "http://id.who.int/icd/entity/1453089907",
      "linearizationReference": "http://id.who.int/icd/release/11/2024-01/mms/1453089907"
    },
    {
      "label": {
        "@language": "en",
        "@value": "injuries of shoulder"
      },
      "foundationReference": "http://id.who.int/icd/entity/1416283029",
      "linearizationReference": "http://id.who.int/icd/release/11/2024-01/mms/1416283029"
    },
    {
      "label": {
        "@language": "en",
        "@value": "Injuries of trunk NOS"
      },
      "foundationReference": "http://id.who.int/icd/entity/1453089907",
      "linearizationReference": "http://id.who.int/icd/release/11/2024-01/mms/1453089907"
    },
    {
      "label": {
        "@language": "en",
        "@value": "insect bite or sting, venomous"
      },
      "foundationReference": "http://id.who.int/icd/entity/1645464025",
      "linearizationReference": "http://id.who.int/icd/release/11/2024-01/mms/1119330136"
    },
    {
      "label": {
        "@language": "en",
        "@value": "fracture of spine NOS"
      },
      "foundationReference": "http://id.who.int/icd/entity/869771751",
      "linearizationReference": "http://id.who.int/icd/release/11/2024-01/mms/869771751"
    },
    {
      "label": {
        "@language": "en",
        "@value": "injuries of clavicle"
      },
      "foundationReference": "http://id.who.int/icd/entity/1416283029",
      "linearizationReference": "http://id.who.int/icd/release/11/2024-01/mms/1416283029"
    },
    {
      "label": {
        "@language": "en",
        "@value": "injuries of scapular region"
      },
      "foundationReference": "http://id.who.int/icd/entity/1416283029",
      "linearizationReference": "http://id.who.int/icd/release/11/2024-01/mms/1416283029"
    },
    {
      "label": {
        "@language": "en",
        "@value": "Frostbite"
      },
      "foundationReference": "http://id.who.int/icd/entity/152692065",
      "linearizationReference": "http://id.who.int/icd/release/11/2024-01/mms/152692065"
    },
    {
      "label": {
        "@language": "en",
        "@value": "injuries of axilla"
      },
      "foundationReference": "http://id.who.int/icd/entity/1416283029",
      "linearizationReference": "http://id.who.int/icd/release/11/2024-01/mms/1416283029"
    },
    {
      "label": {
        "@language": "en",
        "@value": "effects of foreign body in lung"
      },
      "foundationReference": "http://id.who.int/icd/entity/427553982",
      "linearizationReference": "http://id.who.int/icd/release/11/2024-01/mms/427553982"
    },
    {
      "label": {
        "@language": "en",
        "@value": "effects of foreign body in bronchus"
      },
      "foundationReference": "http://id.who.int/icd/entity/734289297",
      "linearizationReference": "http://id.who.int/icd/release/11/2024-01/mms/734289297"
    },
    {
      "label": {
        "@language": "en",
        "@value": "Foreign body in trachea"
      },
      "foundationReference": "http://id.who.int/icd/entity/1318031365",
      "linearizationReference": "http://id.who.int/icd/release/11/2024-01/mms/1318031365"
    },
    {
      "label": {
        "@language": "en",
        "@value": "Foreign body in oesophagus"
      },
      "foundationReference": "http://id.who.int/icd/entity/1644383560",
      "linearizationReference": "http://id.who.int/icd/release/11/2024-01/mms/1644383560"
    },
    {
      "label": {
        "@language": "en",
        "@value": "Burns"
      },
      "foundationReference": "http://id.who.int/icd/entity/163532889",
      "linearizationReference": "http://id.who.int/icd/release/11/2024-01/mms/163532889"
    }
  ]
}