{
  "@context": "http://id.who.int/icd/contexts/contextForLinearizationEntity.json",
  "@id": "http://id.who.int/icd/release/11/2024-01/mms/805506345",
  "parent": [
    "http://id.who.int/icd/release/11/2024-01/mms/326964854"
  ],
  "browserUrl": "https://icd.who.int/browse/2024-01/mms/en#805506345",
  "code": "DA08.13",
  "source": "http://id.who.int/icd/entity/805506345",
  "classKind": "category",
  "title": {
    "@language": "en",
    "@value": "Abfraction"
  },
  "definition": {
    "@language": "en",
    "@value": "Theoretical concept of loss of tooth structure not caused by dental caries"
  },
  "inclusion": [
    {
      "label": {
        "@language": "en",
        "@value": "non-carious cervical lesion"
      }
    }
  ],
  "relatedEntitiesInMaternalChapter": [
    "http://id.who.int/icd/entity/1135143938"
  ],
  "relatedEntitiesInPerinatalChapter": [
    "http://id.who.int/icd/entity/494951911"
  ],
  "indexTerm": [
    {
      "label": {
        "@language": "en",
        "@value": "Abfraction"
      }
    },
    {
      "label": {
        "@language": "en",
        "@value": "non-carious cervical lesion"
      }
    }
  ]
}