{
  "@context": "http://id.who.int/icd/contexts/contextForLinearizationEntity.json",
  "@id": "http://id.who.int/icd/release/11/2024-01/mms/938441059",
  "parent": [
    "http://id.who.int/icd/release/11/2024-01/mms/1885920110"
  ],
  "browserUrl": "https://icd.who.int/browse/2024-01/mms/en#938441059",
  "code": "XM00R9",
  "source": "http://id.who.int/icd/entity/938441059",
  "classKind": "category",
  "title": {
    "@language": "en",
    "@value": "Iloprost"
  },
  "indexTerm": [
    {
      "label": {
        "@language": "en",
        "@value": "Iloprost"
      }
    }
  ]
}