{
  "@context": "http://id.who.int/icd/contexts/contextForLinearizationEntity.json",
  "@id": "http://id.who.int/icd/release/11/2024-01/mms/962107653",
  "parent": [
    "http://id.who.int/icd/release/11/2024-01/mms/1510618119"
  ],
  "browserUrl": "https://icd.who.int/browse/2024-01/mms/en#962107653",
  "code": "2B33.0",
  "source": "http://id.who.int/icd/entity/962107653",
  "classKind": "category",
  "postcoordinationScale": [
    {
      "@id": "http://id.who.int/icd/release/11/2024-01/mms/962107653/postcoordinationScale/hasManifestation",
      "axisName": "http://id.who.int/icd/schema/hasManifestation",
      "requiredPostcoordination": "false",
      "allowMultipleValues": "AllowAlways",
      "scaleEntity": [
        "http://id.who.int/icd/release/11/2024-01/mms/322466810"
      ]
    },
    {
      "@id": "http://id.who.int/icd/release/11/2024-01/mms/962107653/postcoordinationScale/hasSeverity",
      "axisName": "http://id.who.int/icd/schema/hasSeverity",
      "requiredPostcoordination": "false",
      "allowMultipleValues": "NotAllowed",
      "scaleEntity": [
        "http://id.who.int/icd/release/11/2024-01/mms/1863636238",
        "http://id.who.int/icd/release/11/2024-01/mms/885826145",
        "http://id.who.int/icd/release/11/2024-01/mms/1746207012",
        "http://id.who.int/icd/release/11/2024-01/mms/303697349"
      ]
    }
  ],
  "title": {
    "@language": "en",
    "@value": "Acute leukaemia, not elsewhere classified"
  },
  "codingNote": {
    "@language": "en",
    "@value": "Only to be designated in cases with incomplete diagnostics."
  },
  "indexTerm": [
    {
      "label": {
        "@language": "en",
        "@value": "Acute leukaemia, not elsewhere classified"
      }
    },
    {
      "label": {
        "@language": "en",
        "@value": "acute leukaemia of unspecified cell type without mention of remission"
      }
    },
    {
      "label": {
        "@language": "en",
        "@value": "blast cell leukaemia"
      }
    },
    {
      "label": {
        "@language": "en",
        "@value": "blast leukaemia"
      }
    },
    {
      "label": {
        "@language": "en",
        "@value": "blastic leukaemia"
      }
    },
    {
      "label": {
        "@language": "en",
        "@value": "undifferentiated leukaemia"
      }
    },
    {
      "label": {
        "@language": "en",
        "@value": "stem cell leukaemia"
      }
    },
    {
      "label": {
        "@language": "en",
        "@value": "Acute leukaemia of unspecified cell type in complete remission"
      },
      "foundationReference": "http://id.who.int/icd/entity/1657756257"
    }
  ]
}