{
  "@context": "http://id.who.int/icd/contexts/contextForLinearizationEntity.json",
  "@id": "http://id.who.int/icd/release/11/2024-01/mms/977870982",
  "parent": [
    "http://id.who.int/icd/release/11/2024-01/mms/2046015098"
  ],
  "browserUrl": "https://icd.who.int/browse/2024-01/mms/en#977870982",
  "code": "DB97.0",
  "source": "http://id.who.int/icd/entity/977870982",
  "classKind": "category",
  "postcoordinationScale": [
    {
      "@id": "http://id.who.int/icd/release/11/2024-01/mms/977870982/postcoordinationScale/hasManifestation",
      "axisName": "http://id.who.int/icd/schema/hasManifestation",
      "requiredPostcoordination": "false",
      "allowMultipleValues": "AllowAlways",
      "scaleEntity": [
        "http://id.who.int/icd/release/11/2024-01/mms/1020615731"
      ]
    },
    {
      "@id": "http://id.who.int/icd/release/11/2024-01/mms/977870982/postcoordinationScale/course",
      "axisName": "http://id.who.int/icd/schema/course",
      "requiredPostcoordination": "false",
      "allowMultipleValues": "NotAllowed",
      "scaleEntity": [
        "http://id.who.int/icd/release/11/2024-01/mms/786106375",
        "http://id.who.int/icd/release/11/2024-01/mms/490003542"
      ]
    }
  ],
  "title": {
    "@language": "en",
    "@value": "Idiopathic granulomatous hepatitis"
  },
  "relatedEntitiesInMaternalChapter": [
    "http://id.who.int/icd/entity/1135143938"
  ],
  "relatedEntitiesInPerinatalChapter": [
    "http://id.who.int/icd/entity/494951911"
  ],
  "indexTerm": [
    {
      "label": {
        "@language": "en",
        "@value": "Idiopathic granulomatous hepatitis"
      }
    },
    {
      "label": {
        "@language": "en",
        "@value": "granulomatous hepatitis NEC"
      }
    },
    {
      "label": {
        "@language": "en",
        "@value": "granulomatous hepatitis"
      }
    }
  ]
}